package/armstrong.py
armstrong_asmita-1.0.0.dist-info/LICENSE
armstrong_asmita-1.0.0.dist-info/METADATA
armstrong_asmita-1.0.0.dist-info/WHEEL
armstrong_asmita-1.0.0.dist-info/top_level.txt
armstrong_asmita-1.0.0.dist-info/RECORD
