Metadata-Version: 2.1
Name: armstrong-asmita
Version: 1.0.0
Summary: Asmita tarar
Home-page: https://github.com/Akshay311/armstrong
Author: Asmita Tarar
Author-email: asmitatarar@outlook.com
License: MIT
Platform: UNKNOWN
Classifier: License :: OSI Approved :: MIT License
Classifier: Programming Language :: Python :: 3
Classifier: Programming Language :: Python :: 3.7
License-File: LICENSE
